Metadata-Version: 1.0
Name: programWK
Version: 1.0.1
Summary: Good day, please help yourself
Home-page: UNKNOWN
Author: UNKNOWN
Author-email: UNKNOWN
License: UNKNOWN
Platform: UNKNOWN
